rlbcore/__init__.py
rlbcore/api/__init__.py
rlbcore/api/agents.py
rlbcore/api/gym_.py
rlbcore/api/memory.py
rlbcore/api/other.py
rlbcore/api/ui.py
rlbcore/cli/__init__.py
rlbcore/cli/docs.py
rlbcore/cli/list.py
rlbcore/cli/run.py
rlbcore/config.py
rlbcore/evaluators.py
rlbcore/experience.py
rlbcore/external_utils/__init__.py
rlbcore/external_utils/builtins_.py
rlbcore/external_utils/gym_.py
rlbcore/external_utils/numpy_.py
rlbcore/external_utils/other.py
rlbcore/memories/__init__.py
rlbcore/memories/experience_replay/__init__.py
rlbcore/memories/experience_replay/buffers.py
rlbcore/memories/experience_replay/vanilla.py
rlbcore/memory_transforms.py
rlbcore/observers.py
rlbcore/policies.py
rlbcore/py.typed
rlbcore/uis/__init__.py
rlbcore/uis/cli.py
rlbcore/uis/composite.py
rlbcore/uis/rich_.py
rlbcore/uis/wandb_.py
rlbcore-0.3.4.dist-info/entry_points.txt
rlbcore-0.3.4.dist-info/LICENSE
rlbcore-0.3.4.dist-info/WHEEL
rlbcore-0.3.4.dist-info/METADATA
rlbcore-0.3.4.dist-info/RECORD
