Metadata-Version: 2.1
Name: rlbcore
Version: 0.3.4
Summary: Common functionality for all rlbaselines projects
License: MIT
Author: Aditya Gudimella
Author-email: aditya.gudimella@gmail.com
Requires-Python: >=3.10,<4.0
Classifier: License :: OSI Approved :: MIT License
Classifier: Programming Language :: Python :: 3
Classifier: Programming Language :: Python :: 3.10
Classifier: Programming Language :: Python :: 3.11
Provides-Extra: all
Provides-Extra: mlflow
Provides-Extra: test
Provides-Extra: wandb
Requires-Dist: attrs (>=22.1.0,<23.0.0)
Requires-Dist: autoflake (>=1.4,<2.0); extra == "test" or extra == "all"
Requires-Dist: black (>=22.3.0,<23.0.0); extra == "test" or extra == "all"
Requires-Dist: gymnasium (>=0.27.0,<0.28.0)
Requires-Dist: isort (>=5.10.1,<6.0.0); extra == "test" or extra == "all"
Requires-Dist: llvmlite (>=0.39.1,<0.40.0); extra == "test" or extra == "all"
Requires-Dist: mkdocs (>=1.4.2,<2.0.0)
Requires-Dist: mkdocs-macros-plugin (>=0.7.0,<0.8.0)
Requires-Dist: mkdocs-material (>=8.5.11,<9.0.0)
Requires-Dist: mkdocstrings[python] (>=0.19.0,<0.20.0)
Requires-Dist: mlflow (>=2.0.1,<3.0.0); extra == "mlflow" or extra == "all"
Requires-Dist: mypy (>=0.961,<0.962); extra == "test" or extra == "all"
Requires-Dist: numba (>=0.56.4,<0.57.0)
Requires-Dist: omegaconf (>=2.3.0,<3.0.0)
Requires-Dist: pandas (>=1.5.2,<2.0.0); extra == "mlflow" or extra == "all"
Requires-Dist: pydantic (>=1.10.2,<2.0.0)
Requires-Dist: pytest (>=7.2.0,<8.0.0); extra == "test" or extra == "all"
Requires-Dist: pytest-vscodedebug (>=0.1.0,<0.2.0); extra == "test" or extra == "all"
Requires-Dist: pyupgrade (>=2.37.3,<3.0.0); extra == "test" or extra == "all"
Requires-Dist: rich (>=12.6.0,<13.0.0)
Requires-Dist: shimmy[dm-control] (==0.2.0); extra == "test" or extra == "all"
Requires-Dist: toml (>=0.10.2,<0.11.0); extra == "test" or extra == "all"
Requires-Dist: typer[all] (>=0.7.0,<0.8.0)
Requires-Dist: wandb (>=0.13.6,<0.14.0); extra == "wandb" or extra == "all"
Requires-Dist: xdoctest[all] (>=1.1.0,<2.0.0); extra == "test" or extra == "all"
